toshiba_ac_ir_codegen/__init__.py
toshiba_ac_ir_codegen/generator.py
toshiba_ac_ir_codegen-1.0.0.dist-info/LICENSE.txt
toshiba_ac_ir_codegen-1.0.0.dist-info/METADATA
toshiba_ac_ir_codegen-1.0.0.dist-info/WHEEL
toshiba_ac_ir_codegen-1.0.0.dist-info/top_level.txt
toshiba_ac_ir_codegen-1.0.0.dist-info/RECORD
