Metadata-Version: 2.2
Name: toshiba_ac_ir_codegen
Version: 1.0.0
Summary: Toshiba IR Remove Control Code Generator
Home-page: https://github.com/pyscaffold/pyscaffold/
Author: Thierry Ygé
Author-email: tyge@adobe.com
License: MIT
Project-URL: Documentation, https://github.com/tyge68/toshiba-ac
Project-URL: Source, https://github.com/tyge68/toshiba-ac/
Platform: any
Classifier: Development Status :: 4 - Beta
Classifier: Programming Language :: Python
License-File: LICENSE.txt
Requires-Dist: importlib-metadata; python_version < "3.8"
Provides-Extra: testing
Requires-Dist: setuptools; extra == "testing"
Requires-Dist: pytest; extra == "testing"
Requires-Dist: pytest-cov; extra == "testing"
